netbox3/__init__.py
netbox3/api/__init__.py
netbox3/api/base_c.py
netbox3/api/base_ca.py
netbox3/api/circuits.py
netbox3/api/connector.py
netbox3/api/core.py
netbox3/api/dcim.py
netbox3/api/extended_get.py
netbox3/api/extras.py
netbox3/api/ip_addresses.py
netbox3/api/ipam.py
netbox3/api/plugins_ca.py
netbox3/api/status.py
netbox3/api/tenancy.py
netbox3/api/users.py
netbox3/api/virtualization.py
netbox3/api/wireless.py
netbox3/branch/__init__.py
netbox3/branch/nb_branch.py
netbox3/branch/nb_custom.py
netbox3/branch/nb_value.py
netbox3/exceptions.py
netbox3/foragers/__init__.py
netbox3/foragers/base_fa.py
netbox3/foragers/circuits.py
netbox3/foragers/core.py
netbox3/foragers/dcim.py
netbox3/foragers/extras.py
netbox3/foragers/forager.py
netbox3/foragers/ipam.py
netbox3/foragers/ipv4.py
netbox3/foragers/joiner.py
netbox3/foragers/tenancy.py
netbox3/foragers/users.py
netbox3/foragers/virtualization.py
netbox3/foragers/wireless.py
netbox3/helpers.py
netbox3/log.py
netbox3/messages.py
netbox3/nb_api.py
netbox3/nb_cache.py
netbox3/nb_forager.py
netbox3/nb_tree.py
netbox3/py.typed
netbox3/types_.py
netbox3/wrappers.py
netbox3-0.1.14.dist-info/METADATA
netbox3-0.1.14.dist-info/WHEEL
netbox3-0.1.14.dist-info/RECORD
